Workbook
Name ProductCategories: OFFSET(Products!$B$1,1,0,COUNTA(Products!$B:$B)-1,1)
Name Slicer_Month_Helper: #N/A
Name Slicer_Month_Helper1: #N/A
Name Slicer_Region: #N/A
Name Slicer_Region1: #N/A

Sheet PivortTables
A3: Region | B3: Sum of Profit | C3: Sum of Revenue | D3: ProfitMargin %
A4: East | B4: -216983.56 | C4: 104142 | D4: -2.0835356
A5: North | B5: -209380.32 | C5: 87013 | D5: -2.4063108
A6: South | B6: -221336.08 | C6: 124308 | D6: -1.7805458
A7: West | B7: -227022.04 | C7: 125799 | D7: -1.804641
A8: Grand Total | B8: -874722 | C8: 441262 | D8: -1.9823189
A10: Category | B10: Sum of Profit
A11: Accessories | B11: -151551.53
A12: Electronics | B12: -576724.18
A13: Office | B13: -146446.29
A14: Grand Total | B14: -874722
A16: Classification | B16: Sum of CustomerID
A17: Low Value | B17: 21181
A18: Regular | B18: 69745
A19: Grand Total | B19: 90926
A21: Region | B21: Sum of DeliveryDays
A22: East | B22: 92
A23: North | B23: 101
A24: South | B24: 125
A25: West | B25: 122
A26: Grand Total | B26: 440
A28: Category | B28: Sum of Profit
A29: Accessories | B29: -151551.53
A30: Electronics | B30: -576724.18
A31: Office | B31: -146446.29
A32: Grand Total | B32: -874722
A34: Product | B34: Sum of Revenue
A35: Headphones | B35: 92783
A36: Laptop | B36: 100036
A37: Monitor | B37: 100690
A38: Printer | B38: 49991
A39: Tablet | B39: 60019
A40: Grand Total | B40: 403519

Sheet Charts

Sheet Dashboard
G1: {="Dashboard for " & IF(PivortTables!B1="", "All Regions", RegionSlicerCell)} -> Dashboard for All Regions
A2: Total Revenue | B2: Total Profit | C2: Top Customer | D2: On‑Time Delivery %
A3: =SUM(Sales_All!S:S) -> 441262 | B3: =SUM(Sales_All!Y:Y) -> -874722 | C3: =INDEX(Sales_All!D:D, MATCH(MAX(Sales_All!Z:Z), Sales_All!Z:Z, 0)) -> 1017 | D3: =COUNTIF(Sales_All!N:N,"<=3") / COUNTA(Sales_All!N:N) -> 0.30769231
O4: Region | P4: Sum of Profit | Q4: Sum of Revenue | R4: ProfitMargin %
O5: East | P5: -216983.56 | Q5: 104142 | R5: -2.0835356
O6: North | P6: -209380.32 | Q6: 87013 | R6: -2.4063108
O7: South | P7: -221336.08 | Q7: 124308 | R7: -1.7805458
O8: West | P8: -227022.04 | Q8: 125799 | R8: -1.804641
O9: Grand Total | P9: -874722 | Q9: 441262 | R9: -1.9823189
O11: Category | P11: Sum of Profit
O12: Accessories | P12: -151551.53
O13: Electronics | P13: -576724.18
O14: Office | P14: -146446.29
O15: Grand Total | P15: -874722
O17: Classification | P17: Sum of CustomerID
O18: Low Value | P18: 21181
O19: Regular | P19: 69745
O20: Grand Total | P20: 90926
O22: Region | P22: Sum of DeliveryDays
O23: East | P23: 92
O24: North | P24: 101
O25: South | P25: 125
O26: West | P26: 122
O27: Grand Total | P27: 440
O29: Category | P29: Sum of Profit
O30: Accessories | P30: -151551.53
O31: Electronics | P31: -576724.18
O32: Office | P32: -146446.29
O33: Grand Total | P33: -874722
O35: Product | P35: Sum of Revenue
O36: Headphones | P36: 92783
O37: Laptop | P37: 100036
O38: Monitor | P38: 100690
O39: Printer | P39: 49991
O40: Tablet | P40: 60019
O41: Grand Total | P41: 403519

Sheet Sales_All
A1: OrderID | B1: Date | C1: Region | D1: CustomerID | E1: Product | F1: Quantity | G1: UnitPrice | H1: Category | I1: UnitCost | L1: Discount | M1: Month Helper | N1: DeliveryDays | O1: ReturnRate | P1: MonthlyOverhead | Q1: MonthlySalary | R1: MonthlyOther | S1: Revenue | T1: Discounted Revenue | U1: Allocate monthly expenses | V1: Allocated Overhead | W1: Allocated Salary | X1: Allocated Other | Y1: Profit | Z1: total revenue per customer | AA1: Classification | AB1: Category
A2: Q1-001 | B2: 45708.027 | C2: South | D2: 1018 | E2: Tablet | F2: 1 | G2: 730 | H2: =_xlfn.XLOOKUP(E2,Products!$A$2:$A$7,Products!$B$2:$B$7,"Not Found",0) -> Electronics | I2: =_xlfn.XLOOKUP(E2,Products!$A$2:$A$7,Products!$D$2:$D$7,"Not Found", 0) -> 492 | L2: =_xlfn.XLOOKUP(E2,Products!$A$2:$A$7,Products!$E$2:$E$7,"Not Found", 0) -> 0.14 | M2: =EOMONTH(B2,0) -> 45716 | N2: =_xlfn.XLOOKUP(A2, Operations!$A:$A, Operations!$B:$B, 0) -> 5 | O2: =_xlfn.XLOOKUP(A2, Operations!$A:$A, Operations!$C:$C, 0) -> 0.01 | P2: =_xlfn.XLOOKUP(M2, Finance!$A:$A, Finance!$B:$B, 0) -> 43320 | Q2: =_xlfn.XLOOKUP(M2, Finance!$A:$A, Finance!$C:$C, 0) -> 70533 | R2: =_xlfn.XLOOKUP(M2, Finance!$A:$A, Finance!$D:$D, 0) -> 27724 | S2: =F2*G2 -> 730 | T2: =S2*(1-L2) -> 627.8 | U2: =COUNTIF($M$2:$M$97, M2) -> 10 | V2: =P2/U2 -> 4332 | W2: =Q2/U2 -> 7053.3 | X2: =R2/U2 -> 2772.4 | Y2: =S2 - (F2*I2) - V2 - W2 - X2 -> -13919.7 | Z2: =SUMIF($D$2:$D$97, D2, $S$2:$S$97) -> 31997 | AA2: {=_xlfn.IFS(Z2>50000, "VIP", Z2>=20000, "Regular", TRUE, "Low Value")} -> Regular | AB2: =INDEX(Products!$B:$B, MATCH(E2, Products!$A:$A, 0)) -> Electronics
A3: Q1-002 | B3: 45712.237 | C3: South | D3: 1004 | E3: Headphones | F3: 3 | G3: 378 | H3: =_xlfn.XLOOKUP(E3,Products!$A$2:$A$7,Products!$B$2:$B$7,"Not Found",0) -> Accessories | I3: =_xlfn.XLOOKUP(E3,Products!$A$2:$A$7,Products!$D$2:$D$7,"Not Found", 0) -> 323 | L3: =_xlfn.XLOOKUP(E3,Products!$A$2:$A$7,Products!$E$2:$E$7,"Not Found", 0) -> 0.1 | M3: =EOMONTH(B3,0) -> 45716 | N3: =_xlfn.XLOOKUP(A3, Operations!$A:$A, Operations!$B:$B, 0) -> 2 | O3: =_xlfn.XLOOKUP(A3, Operations!$A:$A, Operations!$C:$C, 0) -> 0.03 | P3: =_xlfn.XLOOKUP(M3, Finance!$A:$A, Finance!$B:$B, 0) -> 43320 | Q3: =_xlfn.XLOOKUP(M3, Finance!$A:$A, Finance!$C:$C, 0) -> 70533 | R3: =_xlfn.XLOOKUP(M3, Finance!$A:$A, Finance!$D:$D, 0) -> 27724 | S3: =F3*G3 -> 1134 | T3: =S3*(1-L3) -> 1020.6 | U3: =COUNTIF($M$2:$M$97, M3) -> 10 | V3: =P3/U3 -> 4332 | W3: =Q3/U3 -> 7053.3 | X3: =R3/U3 -> 2772.4 | Y3: =S3 - (F3*I3) - V3 - W3 - X3 -> -13992.7 | Z3: =SUMIF($D$2:$D$97, D3, $S$2:$S$97) -> 8004 | AA3: {=_xlfn.IFS(Z3>50000, "VIP", Z3>=20000, "Regular", TRUE, "Low Value")} -> Low Value | AB3: =INDEX(Products!$B:$B, MATCH(E3, Products!$A:$A, 0)) -> Accessories
A4: Q1-003 | B4: 45736.268 | C4: West | D4: 1005 | E4: Monitor | F4: 1 | G4: 585 | H4: =_xlfn.XLOOKUP(E4,Products!$A$2:$A$7,Products!$B$2:$B$7,"Not Found",0) -> Electronics | I4: =_xlfn.XLOOKUP(E4,Products!$A$2:$A$7,Products!$D$2:$D$7,"Not Found", 0) -> 463 | L4: =_xlfn.XLOOKUP(E4,Products!$A$2:$A$7,Products!$E$2:$E$7,"Not Found", 0) -> 0.23 | M4: =EOMONTH(B4,0) -> 45747 | N4: =_xlfn.XLOOKUP(A4, Operations!$A:$A, Operations!$B:$B, 0) -> 6 | O4: =_xlfn.XLOOKUP(A4, Operations!$A:$A, Operations!$C:$C, 0) -> 0.05 | P4: =_xlfn.XLOOKUP(M4, Finance!$A:$A, Finance!$B:$B, 0) -> 34147 | Q4: =_xlfn.XLOOKUP(M4, Finance!$A:$A, Finance!$C:$C, 0) -> 63890 | R4: =_xlfn.XLOOKUP(M4, Finance!$A:$A, Finance!$D:$D, 0) -> 17738 | S4: =F4*G4 -> 585 | T4: =S4*(1-L4) -> 450.45 | U4: =COUNTIF($M$2:$M$97, M4) -> 10 | V4: =P4/U4 -> 3414.7 | W4: =Q4/U4 -> 6389 | X4: =R4/U4 -> 1773.8 | Y4: =S4 - (F4*I4) - V4 - W4 - X4 -> -11455.5 | Z4: =SUMIF($D$2:$D$97, D4, $S$2:$S$97) -> 24821 | AA4: {=_xlfn.IFS(Z4>50000, "VIP", Z4>=20000, "Regular", TRUE, "Low Value")} -> Regular | AB4: =INDEX(Products!$B:$B, MATCH(E4, Products!$A:$A, 0)) -> Electronics
A5: Q1-004 | B5: 45703.571 | C5: East | D5: 1018 | E5: Smartphone | F5: 8 | G5: 726 | H5: =_xlfn.XLOOKUP(E5,Products!$A$2:$A$7,Products!$B$2:$B$7,"Not Found",0) -> Electronics | I5: =_xlfn.XLOOKUP(E5,Products!$A$2:$A$7,Products!$D$2:$D$7,"Not Found", 0) -> 97 | L5: =_xlfn.XLOOKUP(E5,Products!$A$2:$A$7,Products!$E$2:$E$7,"Not Found", 0) -> 0.08 | M5: =EOMONTH(B5,0) -> 45716 | N5: =_xlfn.XLOOKUP(A5, Operations!$A:$A, Operations!$B:$B, 0) -> 4 | O5: =_xlfn.XLOOKUP(A5, Operations!$A:$A, Operations!$C:$C, 0) -> 0.07 | P5: =_xlfn.XLOOKUP(M5, Finance!$A:$A, Finance!$B:$B, 0) -> 43320 | Q5: =_xlfn.XLOOKUP(M5, Finance!$A:$A, Finance!$C:$C, 0) -> 70533 | R5: =_xlfn.XLOOKUP(M5, Finance!$A:$A, Finance!$D:$D, 0) -> 27724 | S5: =F5*G5 -> 5808 | T5: =S5*(1-L5) -> 5343.36 | U5: =COUNTIF($M$2:$M$97, M5) -> 10 | V5: =P5/U5 -> 4332 | W5: =Q5/U5 -> 7053.3 | X5: =R5/U5 -> 2772.4 | Y5: =S5 - (F5*I5) - V5 - W5 - X5 -> -9125.7 | Z5: =SUMIF($D$2:$D$97, D5, $S$2:$S$97) -> 31997 | AA5: {=_xlfn.IFS(Z5>50000, "VIP", Z5>=20000, "Regular", TRUE, "Low Value")} -> Regular | AB5: =INDEX(Products!$B:$B, MATCH(E5, Products!$A:$A, 0)) -> Electronics
A6: Q1-005 | B6: 45663.686 | C6: North | D6: 1012 | E6: Laptop | F6: 2 | G6: 709 | H6: =_xlfn.XLOOKUP(E6,Products!$A$2:$A$7,Products!$B$2:$B$7,"Not Found",0) -> Electronics | I6: =_xlfn.XLOOKUP(E6,Products!$A$2:$A$7,Products!$D$2:$D$7,"Not Found", 0) -> 469 | L6: =_xlfn.XLOOKUP(E6,Products!$A$2:$A$7,Products!$E$2:$E$7,"Not Found", 0) -> 0.22 | M6: =EOMONTH(B6,0) -> 45688 | N6: =_xlfn.XLOOKUP(A6, Operations!$A:$A, Operations!$B:$B, 0) -> 5 | O6: =_xlfn.XLOOKUP(A6, Operations!$A:$A, Operations!$C:$C, 0) -> 0.03 | P6: =_xlfn.XLOOKUP(M6, Finance!$A:$A, Finance!$B:$B, 0) -> 25640 | Q6: =_xlfn.XLOOKUP(M6, Finance!$A:$A, Finance!$C:$C, 0) -> 60082 | R6: =_xlfn.XLOOKUP(M6, Finance!$A:$A, Finance!$D:$D, 0) -> 21492 | S6: =F6*G6 -> 1418 | T6: =S6*(1-L6) -> 1106.04 | U6: =COUNTIF($M$2:$M$97, M6) -> 10 | V6: =P6/U6 -> 2564 | W6: =Q6/U6 -> 6008.2 | X6: =R6/U6 -> 2149.2 | Y6: =S6 - (F6*I6) - V6 - W6 - X6 -> -10241.4 | Z6: =SUMIF($D$2:$D$97, D6, $S$2:$S$97) -> 8379 | AA6: {=_xlfn.IFS(Z6>50000, "VIP", Z6>=20000, "Regular", TRUE, "Low Value")} -> Low Value | AB6: =INDEX(Products!$B:$B, MATCH(E6, Products!$A:$A, 0)) -> Electronics
A7: Q1-006 | B7: 45716.227 | C7: East | D7: 1013 | E7: Laptop | F7: 8 | G7: 1817 | H7: =_xlfn.XLOOKUP(E7,Products!$A$2:$A$7,Products!$B$2:$B$7,"Not Found",0) -> Electronics | I7: =_xlfn.XLOOKUP(E7,Products!$A$2:$A$7,Products!$D$2:$D$7,"Not Found", 0) -> 469 | L7: =_xlfn.XLOOKUP(E7,Products!$A$2:$A$7,Products!$E$2:$E$7,"Not Found", 0) -> 0.22 | M7: =EOMONTH(B7,0) -> 45716 | N7: =_xlfn.XLOOKUP(A7, Operations!$A:$A, Operations!$B:$B, 0) -> 5 | O7: =_xlfn.XLOOKUP(A7, Operations!$A:$A, Operations!$C:$C, 0) -> 0.06 | P7: =_xlfn.XLOOKUP(M7, Finance!$A:$A, Finance!$B:$B, 0) -> 43320 | Q7: =_xlfn.XLOOKUP(M7, Finance!$A:$A, Finance!$C:$C, 0) -> 70533 | R7: =_xlfn.XLOOKUP(M7, Finance!$A:$A, Finance!$D:$D, 0) -> 27724 | S7: =F7*G7 -> 14536 | T7: =S7*(1-L7) -> 11338.08 | U7: =COUNTIF($M$2:$M$97, M7) -> 10 | V7: =P7/U7 -> 4332 | W7: =Q7/U7 -> 7053.3 | X7: =R7/U7 -> 2772.4 | Y7: =S7 - (F7*I7) - V7 - W7 - X7 -> -3373.7 | Z7: =SUMIF($D$2:$D$97, D7, $S$2:$S$97) -> 17364 | AA7: {=_xlfn.IFS(Z7>50000, "VIP", Z7>=20000, "Regular", TRUE, "Low Value")} -> Low Value | AB7: =INDEX(Products!$B:$B, MATCH(E7, Products!$A:$A, 0)) -> Electronics
A8: Q1-007 | B8: 45735.116 | C8: South | D8: 1017 | E8: Tablet | F8: 9 | G8: 1976 | H8: =_xlfn.XLOOKUP(E8,Products!$A$2:$A$7,Products!$B$2:$B$7,"Not Found",0) -> Electronics | I8: =_xlfn.XLOOKUP(E8,Products!$A$2:$A$7,Products!$D$2:$D$7,"Not Found", 0) -> 492 | L8: =_xlfn.XLOOKUP(E8,Products!$A$2:$A$7,Products!$E$2:$E$7,"Not Found", 0) -> 0.14 | M8: =EOMONTH(B8,0) -> 45747 | N8: =_xlfn.XLOOKUP(A8, Operations!$A:$A, Operations!$B:$B, 0) -> 4 | O8: =_xlfn.XLOOKUP(A8, Operations!$A:$A, Operations!$C:$C, 0) -> 0.02 | P8: =_xlfn.XLOOKUP(M8, Finance!$A:$A, Finance!$B:$B, 0) -> 34147 | Q8: =_xlfn.XLOOKUP(M8, Finance!$A:$A, Finance!$C:$C, 0) -> 63890 | R8: =_xlfn.XLOOKUP(M8, Finance!$A:$A, Finance!$D:$D, 0) -> 17738 | S8: =F8*G8 -> 17784 | T8: =S8*(1-L8) -> 15294.24 | U8: =COUNTIF($M$2:$M$97, M8) -> 10 | V8: =P8/U8 -> 3414.7 | W8: =Q8/U8 -> 6389 | X8: =R8/U8 -> 1773.8 | Y8: =S8 - (F8*I8) - V8 - W8 - X8 -> 1778.5 | Z8: =SUMIF($D$2:$D$97, D8, $S$2:$S$97) -> 38912 | AA8: {=_xlfn.IFS(Z8>50000, "VIP", Z8>=20000, "Regular", TRUE, "Low Value")} -> Regular | AB8: =INDEX(Products!$B:$B, MATCH(E8, Products!$A:$A, 0)) -> Electronics
A9: Q1-008 | B9: 45707.394 | C9: South | D9: 1014 | E9: Tablet | F9: 5 | G9: 1134 | H9: =_xlfn.XLOOKUP(E9,Products!$A$2:$A$7,Products!$B$2:$B$7,"Not Found",0) -> Electronics | I9: =_xlfn.XLOOKUP(E9,Products!$A$2:$A$7,Products!$D$2:$D$7,"Not Found", 0) -> 492 | L9: =_xlfn.XLOOKUP(E9,Products!$A$2:$A$7,Products!$E$2:$E$7,"Not Found", 0) -> 0.14 | M9: =EOMONTH(B9,0) -> 45716 | N9: =_xlfn.XLOOKUP(A9, Operations!$A:$A, Operations!$B:$B, 0) -> 8 | O9: =_xlfn.XLOOKUP(A9, Operations!$A:$A, Operations!$C:$C, 0) -> 0.07 | P9: =_xlfn.XLOOKUP(M9, Finance!$A:$A, Finance!$B:$B, 0) -> 43320 | Q9: =_xlfn.XLOOKUP(M9, Finance!$A:$A, Finance!$C:$C, 0) -> 70533 | R9: =_xlfn.XLOOKUP(M9, Finance!$A:$A, Finance!$D:$D, 0) -> 27724 | S9: =F9*G9 -> 5670 | T9: =S9*(1-L9) -> 4876.2 | U9: =COUNTIF($M$2:$M$97, M9) -> 10 | V9: =P9/U9 -> 4332 | W9: =Q9/U9 -> 7053.3 | X9: =R9/U9 -> 2772.4 | Y9: =S9 - (F9*I9) - V9 - W9 - X9 -> -10947.7 | Z9: =SUMIF($D$2:$D$97, D9, $S$2:$S$97) -> 31571 | AA9: {=_xlfn.IFS(Z9>50000, "VIP", Z9>=20000, "Regular", TRUE, "Low Value")} -> Regular | AB9: =INDEX(Products!$B:$B, MATCH(E9, Products!$A:$A, 0)) -> Electronics
A10: Q1-009 | B10: 45671.497 | C10: South | D10: 1020 | E10: Printer | F10: 1 | G10: 1220 | H10: =_xlfn.XLOOKUP(E10,Products!$A$2:$A$7,Products!$B$2:$B$7,"Not Found",0) -> Office | I10: =_xlfn.XLOOKUP(E10,Products!$A$2:$A$7,Products!$D$2:$D$7,"Not Found", 0) -> 136 | L10: =_xlfn.XLOOKUP(E10,Products!$A$2:$A$7,Products!$E$2:$E$7,"Not Found", 0) -> 0.1 | M10: =EOMONTH(B10,0) -> 45688 | N10: =_xlfn.XLOOKUP(A10, Operations!$A:$A, Operations!$B:$B, 0) -> 2 | O10: =_xlfn.XLOOKUP(A10, Operations!$A:$A, Operations!$C:$C, 0) -> 0.08 | P10: =_xlfn.XLOOKUP(M10, Finance!$A:$A, Finance!$B:$B, 0) -> 25640 | Q10: =_xlfn.XLOOKUP(M10, Finance!$A:$A, Finance!$C:$C, 0) -> 60082 | R10: =_xlfn.XLOOKUP(M10, Finance!$A:$A, Finance!$D:$D, 0) -> 21492 | S10: =F10*G10 -> 1220 | T10: =S10*(1-L10) -> 1098 | U10: =COUNTIF($M$2:$M$97, M10) -> 10 | V10: =P10/U10 -> 2564 | W10: =Q10/U10 -> 6008.2 | X10: =R10/U10 -> 2149.2 | Y10: =S10 - (F10*I10) - V10 - W10 - X10 -> -9637.4 | Z10: =SUMIF($D$2:$D$97, D10, $S$2:$S$97) -> 21494 | AA10: {=_xlfn.IFS(Z10>50000, "VIP", Z10>=20000, "Regular", TRUE, "Low Value")} -> Regular | AB10: =INDEX(Products!$B:$B, MATCH(E10, Products!$A:$A, 0)) -> Office
A11: Q1-010 | B11: 45743.202 | C11: West | D11: 1010 | E11: Headphones | F11: 2 | G11: 283 | H11: =_xlfn.XLOOKUP(E11,Products!$A$2:$A$7,Products!$B$2:$B$7,"Not Found",0) -> Accessories | I11: =_xlfn.XLOOKUP(E11,Products!$A$2:$A$7,Products!$D$2:$D$7,"Not Found", 0) -> 323 | L11: =_xlfn.XLOOKUP(E11,Products!$A$2:$A$7,Products!$E$2:$E$7,"Not Found", 0) -> 0.1 | M11: =EOMONTH(B11,0) -> 45747 | N11: =_xlfn.XLOOKUP(A11, Operations!$A:$A, Operations!$B:$B, 0) -> 2 | O11: =_xlfn.XLOOKUP(A11, Operations!$A:$A, Operations!$C:$C, 0) -> 0.08 | P11: =_xlfn.XLOOKUP(M11, Finance!$A:$A, Finance!$B:$B, 0) -> 34147 | Q11: =_xlfn.XLOOKUP(M11, Finance!$A:$A, Finance!$C:$C, 0) -> 63890 | R11: =_xlfn.XLOOKUP(M11, Finance!$A:$A, Finance!$D:$D, 0) -> 17738 | S11: =F11*G11 -> 566 | T11: =S11*(1-L11) -> 509.4 | U11: =COUNTIF($M$2:$M$97, M11) -> 10 | V11: =P11/U11 -> 3414.7 | W11: =Q11/U11 -> 6389 | X11: =R11/U11 -> 1773.8 | Y11: =S11 - (F11*I11) - V11 - W11 - X11 -> -11657.5 | Z11: =SUMIF($D$2:$D$97, D11, $S$2:$S$97) -> 23446 | AA11: {=_xlfn.IFS(Z11>50000, "VIP", Z11>=20000, "Regular", TRUE, "Low Value")} -> Regular | AB11: =INDEX(Products!$B:$B, MATCH(E11, Products!$A:$A, 0)) -> Accessories
A12: Q1-011 | B12: 45684.929 | C12: West | D12: 1019 | E12: Laptop | F12: 9 | G12: 417 | H12: =_xlfn.XLOOKUP(E12,Products!$A$2:$A$7,Products!$B$2:$B$7,"Not Found",0) -> Electronics | I12: =_xlfn.XLOOKUP(E12,Products!$A$2:$A$7,Products!$D$2:$D$7,"Not Found", 0) -> 469 | L12: =_xlfn.XLOOKUP(E12,Products!$A$2:$A$7,Products!$E$2:$E$7,"Not Found", 0) -> 0.22 | M12: =EOMONTH(B12,0) -> 45688 | N12: =_xlfn.XLOOKUP(A12, Operations!$A:$A, Operations!$B:$B, 0) -> 8 | O12: =_xlfn.XLOOKUP(A12, Operations!$A:$A, Operations!$C:$C, 0) -> 0.06 | P12: =_xlfn.XLOOKUP(M12, Finance!$A:$A, Finance!$B:$B, 0) -> 25640 | Q12: =_xlfn.XLOOKUP(M12, Finance!$A:$A, Finance!$C:$C, 0) -> 60082 | R12: =_xlfn.XLOOKUP(M12, Finance!$A:$A, Finance!$D:$D, 0) -> 21492 | S12: =F12*G12 -> 3753 | T12: =S12*(1-L12) -> 2927.34 | U12: =COUNTIF($M$2:$M$97, M12) -> 10 | V12: =P12/U12 -> 2564 | W12: =Q12/U12 -> 6008.2 | X12: =R12/U12 -> 2149.2 | Y12: =S12 - (F12*I12) - V12 - W12 - X12 -> -11189.4 | Z12: =SUMIF($D$2:$D$97, D12, $S$2:$S$97) -> 20633 | AA12: {=_xlfn.IFS(Z12>50000, "VIP", Z12>=20000, "Regular", TRUE, "Low Value")} -> Regular | AB12: =INDEX(Products!$B:$B, MATCH(E12, Products!$A:$A, 0)) -> Electronics
A13: Q1-012 | B13: 45662.79 | C13: South | D13: 1016 | E13: Laptop | F13: 3 | G13: 1692 | H13: =_xlfn.XLOOKUP(E13,Products!$A$2:$A$7,Products!$B$2:$B$7,"Not Found",0) -> Electronics | I13: =_xlfn.XLOOKUP(E13,Products!$A$2:$A$7,Products!$D$2:$D$7,"Not Found", 0) -> 469 | L13: =_xlfn.XLOOKUP(E13,Products!$A$2:$A$7,Products!$E$2:$E$7,"Not Found", 0) -> 0.22 | M13: =EOMONTH(B13,0) -> 45688 | N13: =_xlfn.XLOOKUP(A13, Operations!$A:$A, Operations!$B:$B, 0) -> 8 | O13: =_xlfn.XLOOKUP(A13, Operations!$A:$A, Operations!$C:$C, 0) -> 0.03 | P13: =_xlfn.XLOOKUP(M13, Finance!$A:$A, Finance!$B:$B, 0) -> 25640 | Q13: =_xlfn.XLOOKUP(M13, Finance!$A:$A, Finance!$C:$C, 0) -> 60082 | R13: =_xlfn.XLOOKUP(M13, Finance!$A:$A, Finance!$D:$D, 0) -> 21492 | S13: =F13*G13 -> 5076 | T13: =S13*(1-L13) -> 3959.28 | U13: =COUNTIF($M$2:$M$97, M13) -> 10 | V13: =P13/U13 -> 2564 | W13: =Q13/U13 -> 6008.2 | X13: =R13/U13 -> 2149.2 | Y13: =S13 - (F13*I13) - V13 - W13 - X13 -> -7052.4 | Z13: =SUMIF($D$2:$D$97, D13, $S$2:$S$97) -> 22009 | AA13: {=_xlfn.IFS(Z13>50000, "VIP", Z13>=20000, "Regular", TRUE, "Low Value")} -> Regular | AB13: =INDEX(Products!$B:$B, MATCH(E13, Products!$A:$A, 0)) -> Electronics
... A91: Q2-030 | B91: 45752.783 | C91: East | D91: 1006 | E91: Headphones | F91: 2 | G91: 1035 | H91: =_xlfn.XLOOKUP(E91,Products!$A$2:$A$7,Products!$B$2:$B$7,"Not Found",0) -> Accessories | I91: =_xlfn.XLOOKUP(E91,Products!$A$2:$A$7,Products!$D$2:$D$7,"Not Found", 0) -> 323 | L91: =_xlfn.XLOOKUP(E91,Products!$A$2:$A$7,Products!$E$2:$E$7,"Not Found", 0) -> 0.1 | M91: =EOMONTH(B91,0) -> 45777 | N91: =_xlfn.XLOOKUP(A91, Operations!$A:$A, Operations!$B:$B, 0) -> 8 | O91: =_xlfn.XLOOKUP(A91, Operations!$A:$A, Operations!$C:$C, 0) -> 0.04 | P91: =_xlfn.XLOOKUP(M91, Finance!$A:$A, Finance!$B:$B, 0) -> 44423 | Q91: =_xlfn.XLOOKUP(M91, Finance!$A:$A, Finance!$C:$C, 0) -> 90674 | R91: =_xlfn.XLOOKUP(M91, Finance!$A:$A, Finance!$D:$D, 0) -> 21152 | S91: =F91*G91 -> 2070 | T91: =S91*(1-L91) -> 1863 | U91: =COUNTIF($M$2:$M$97, M91) -> 14 | V91: =P91/U91 -> 3173.0714 | W91: =Q91/U91 -> 6476.7143 | X91: =R91/U91 -> 1510.8571 | Y91: =S91 - (F91*I91) - V91 - W91 - X91 -> -9736.6429 | Z91: =SUMIF($D$2:$D$97, D91, $S$2:$S$97) -> 34295 | AA91: {=_xlfn.IFS(Z91>50000, "VIP", Z91>=20000, "Regular", TRUE, "Low Value")} -> Regular | AB91: =INDEX(Products!$B:$B, MATCH(E91, Products!$A:$A, 0)) -> Accessories

Sheet Region_Summary
A2: {=_xlfn.UNIQUE(Sales_All!$C$2:$C$91)} -> South | B2: {=COUNTIF(Sales_All!$C$2:$C$91,_xlfn.ANCHORARRAY( A2))} -> 23 | C2: {=AVERAGEIF(Sales_All!$C$2:$C$91,_xlfn.ANCHORARRAY( A2), Sales_All!$N$2:$N$91)} -> 5.4347826
A3: West | B3: 24 | C3: 5.0833333
A4: East | B4: 21 | C4: 4.3809524
A5: North | B5: 22 | C5: 4.5909091

Sheet Products
A1: Product | B1: Category | C1: UnitPrice | D1: UnitCost | E1: Discount
A2: Laptop | B2: Electronics | C2: 1299 | D2: 469 | E2: 0.22
A3: Tablet | B3: Electronics | C3: 1613 | D3: 492 | E3: 0.14
A4: Smartphone | B4: Electronics | C4: 1402 | D4: 97 | E4: 0.08
A5: Headphones | B5: Accessories | C5: 106 | D5: 323 | E5: 0.1
A6: Monitor | B6: Electronics | C6: 396 | D6: 463 | E6: 0.23
A7: Printer | B7: Office | C7: 1635 | D7: 136 | E7: 0.1

Sheet Customers
A1: CustomerID | B1: FirstName | C1: LastName | D1: Email | E1: Region | F1: First Name | G1: Last Name | H1: Email Domain | I1: products per customer
A2: 1001 | B2: Naledi | C2: Pillay | D2: naledi.pillay@example.com | E2: East | F2: =LEFT(D2, FIND(".", D2) - 1) -> naledi | G2: =MID(D2,FIND(".",D2)+1,FIND("@",D2)-FIND(".",D2)-1) -> pillay | H2: =RIGHT(D2, LEN(D2) - FIND("@", D2)) -> example.com | I2: {=_xlfn.TEXTJOIN(", ", TRUE, IF(Sales_All!$D$2:$D$97 = A2, Sales_All!$E$2:$E$97, ""))} -> Printer, Monitor, Monitor, Monitor, Laptop, Laptop, Smartphone, Headphones
A3: 1002 | B3: Michael | C3: Van Wyk | D3: michael.van wyk@example.com | E3: East | F3: =LEFT(D3, FIND(".", D3) - 1) -> michael | G3: =MID(D3,FIND(".",D3)+1,FIND("@",D3)-FIND(".",D3)-1) -> van wyk | H3: =RIGHT(D3, LEN(D3) - FIND("@", D3)) -> example.com | I3: {=_xlfn.TEXTJOIN(", ", TRUE, IF(Sales_All!$D$2:$D$97 = A3, Sales_All!$E$2:$E$97, ""))} -> Laptop, Headphones, Laptop, Tablet
A4: 1003 | B4: Naledi | C4: Botha | D4: naledi.botha@example.com | E4: East | F4: =LEFT(D4, FIND(".", D4) - 1) -> naledi | G4: =MID(D4,FIND(".",D4)+1,FIND("@",D4)-FIND(".",D4)-1) -> botha | H4: =RIGHT(D4, LEN(D4) - FIND("@", D4)) -> example.com | I4: {=_xlfn.TEXTJOIN(", ", TRUE, IF(Sales_All!$D$2:$D$97 = A4, Sales_All!$E$2:$E$97, ""))} -> Printer, Monitor, Monitor, Headphones
A5: 1004 | B5: Naledi | C5: Botha | D5: naledi.botha@example.com | E5: North | F5: =LEFT(D5, FIND(".", D5) - 1) -> naledi | G5: =MID(D5,FIND(".",D5)+1,FIND("@",D5)-FIND(".",D5)-1) -> botha | H5: =RIGHT(D5, LEN(D5) - FIND("@", D5)) -> example.com | I5: {=_xlfn.TEXTJOIN(", ", TRUE, IF(Sales_All!$D$2:$D$97 = A5, Sales_All!$E$2:$E$97, ""))} -> Headphones, Printer, Laptop
A6: 1005 | B6: Michael | C6: Johnson | D6: michael.johnson@example.com | E6: North | F6: =LEFT(D6, FIND(".", D6) - 1) -> michael | G6: =MID(D6,FIND(".",D6)+1,FIND("@",D6)-FIND(".",D6)-1) -> johnson | H6: =RIGHT(D6, LEN(D6) - FIND("@", D6)) -> example.com | I6: {=_xlfn.TEXTJOIN(", ", TRUE, IF(Sales_All!$D$2:$D$97 = A6, Sales_All!$E$2:$E$97, ""))} -> Monitor, Printer, Printer, Tablet, Printer
A7: 1006 | B7: Emily | C7: Johnson | D7: emily.johnson@example.com | E7: South | F7: =LEFT(D7, FIND(".", D7) - 1) -> emily | G7: =MID(D7,FIND(".",D7)+1,FIND("@",D7)-FIND(".",D7)-1) -> johnson | H7: =RIGHT(D7, LEN(D7) - FIND("@", D7)) -> example.com | I7: {=_xlfn.TEXTJOIN(", ", TRUE, IF(Sales_All!$D$2:$D$97 = A7, Sales_All!$E$2:$E$97, ""))} -> Laptop, Monitor, Headphones, Monitor, Laptop, Headphones
A8: 1007 | B8: Michael | C8: Nguyen | D8: michael.nguyen@example.com | E8: West | F8: =LEFT(D8, FIND(".", D8) - 1) -> michael | G8: =MID(D8,FIND(".",D8)+1,FIND("@",D8)-FIND(".",D8)-1) -> nguyen | H8: =RIGHT(D8, LEN(D8) - FIND("@", D8)) -> example.com | I8: {=_xlfn.TEXTJOIN(", ", TRUE, IF(Sales_All!$D$2:$D$97 = A8, Sales_All!$E$2:$E$97, ""))} -> Monitor, Laptop, Smartphone, Monitor
A9: 1008 | B9: Sipho | C9: Johnson | D9: sipho.johnson@example.com | E9: East | F9: =LEFT(D9, FIND(".", D9) - 1) -> sipho | G9: =MID(D9,FIND(".",D9)+1,FIND("@",D9)-FIND(".",D9)-1) -> johnson | H9: =RIGHT(D9, LEN(D9) - FIND("@", D9)) -> example.com | I9: {=_xlfn.TEXTJOIN(", ", TRUE, IF(Sales_All!$D$2:$D$97 = A9, Sales_All!$E$2:$E$97, ""))} -> Smartphone, Headphones, Laptop
A10: 1009 | B10: Sarah | C10: Nguyen | D10: sarah.nguyen@example.com | E10: North | F10: =LEFT(D10, FIND(".", D10) - 1) -> sarah | G10: =MID(D10,FIND(".",D10)+1,FIND("@",D10)-FIND(".",D10)-1) -> nguyen | H10: =RIGHT(D10, LEN(D10) - FIND("@", D10)) -> example.com | I10: {=_xlfn.TEXTJOIN(", ", TRUE, IF(Sales_All!$D$2:$D$97 = A10, Sales_All!$E$2:$E$97, ""))} -> Monitor, Headphones, Smartphone, Laptop, Printer, Smartphone
A11: 1010 | B11: John | C11: Brown | D11: john.brown@example.com | E11: East | F11: =LEFT(D11, FIND(".", D11) - 1) -> john | G11: =MID(D11,FIND(".",D11)+1,FIND("@",D11)-FIND(".",D11)-1) -> brown | H11: =RIGHT(D11, LEN(D11) - FIND("@", D11)) -> example.com | I11: {=_xlfn.TEXTJOIN(", ", TRUE, IF(Sales_All!$D$2:$D$97 = A11, Sales_All!$E$2:$E$97, ""))} -> Headphones, Headphones, Smartphone, Smartphone, Monitor, Printer, Printer
A12: 1011 | B12: John | C12: Smith | D12: john.smith@example.com | E12: South | F12: =LEFT(D12, FIND(".", D12) - 1) -> john | G12: =MID(D12,FIND(".",D12)+1,FIND("@",D12)-FIND(".",D12)-1) -> smith | H12: =RIGHT(D12, LEN(D12) - FIND("@", D12)) -> example.com | I12: {=_xlfn.TEXTJOIN(", ", TRUE, IF(Sales_All!$D$2:$D$97 = A12, Sales_All!$E$2:$E$97, ""))} -> Printer, Tablet, Headphones
A13: 1012 | B13: Naledi | C13: Van Wyk | D13: naledi.van wyk@example.com | E13: East | F13: =LEFT(D13, FIND(".", D13) - 1) -> naledi | G13: =MID(D13,FIND(".",D13)+1,FIND("@",D13)-FIND(".",D13)-1) -> van wyk | H13: =RIGHT(D13, LEN(D13) - FIND("@", D13)) -> example.com | I13: {=_xlfn.TEXTJOIN(", ", TRUE, IF(Sales_All!$D$2:$D$97 = A13, Sales_All!$E$2:$E$97, ""))} -> Laptop, Printer, Monitor, Headphones
... A29: 1018 | B29: Michael | C29: Mlambo | D29: michael.mlambo@example.com | E29: South | F29: =LEFT(D29, FIND(".", D29) - 1) -> michael | G29: =MID(D29,FIND(".",D29)+1,FIND("@",D29)-FIND(".",D29)-1) -> mlambo | H29: =RIGHT(D29, LEN(D29) - FIND("@", D29)) -> example.com | I29: {=_xlfn.TEXTJOIN(", ", TRUE, IF(Sales_All!$D$2:$D$97 = A29, Sales_All!$E$2:$E$97, ""))} -> Tablet, Smartphone, Monitor, Laptop, Headphones, Headphones

Sheet Validation
A1: East
A2: West
A3: North
A4: South

Sheet Operations
A1: OrderID | B1: DeliveryDays | C1: ReturnRate
A2: Q1-001 | B2: 5 | C2: 0.01
A3: Q1-002 | B3: 2 | C3: 0.03
A4: Q1-003 | B4: 6 | C4: 0.05
A5: Q1-004 | B5: 4 | C5: 0.07
A6: Q1-005 | B6: 5 | C6: 0.03
A7: Q1-006 | B7: 5 | C7: 0.06
A8: Q1-007 | B8: 4 | C8: 0.02
A9: Q1-008 | B9: 8 | C9: 0.07
A10: Q1-009 | B10: 2 | C10: 0.08
A11: Q1-010 | B11: 2 | C11: 0.08
A12: Q1-011 | B12: 8 | C12: 0.06
A13: Q1-012 | B13: 8 | C13: 0.03
... A91: Q3-030 | B91: 5 | C91: 0.09

Sheet Finance
A1: Month | B1: Overheads | C1: Salaries | D1: OtherExpenses
A2: 45688 | B2: 25640 | C2: 60082 | D2: 21492
A3: 45716 | B3: 43320 | C3: 70533 | D3: 27724
A4: 45747 | B4: 34147 | C4: 63890 | D4: 17738
A5: 45777 | B5: 44423 | C5: 90674 | D5: 21152
A6: 45808 | B6: 32119 | C6: 55646 | D6: 19723
A7: 45838 | B7: 20079 | C7: 99954 | D7: 15769
A8: 45869 | B8: 36304 | C8: 63297 | D8: 25453
A9: 45900 | B9: 36734 | C9: 93760 | D9: 16230
A10: 45930 | B10: 34260 | C10: 70760 | D10: 28818
